pydantic_sdk/__init__.py
pydantic_sdk-0.0.2.dist-info/METADATA
pydantic_sdk-0.0.2.dist-info/WHEEL
pydantic_sdk-0.0.2.dist-info/licenses/LICENSE
pydantic_sdk-0.0.2.dist-info/RECORD
