Metadata-Version: 2.1
Name: pydantic-sdk
Version: 0.0.2
Summary: Coming Soon
Author-email: Samuel Colvin <s@muelcolvin.com>
License: The MIT License (MIT)
License-File: LICENSE
Classifier: Development Status :: 1 - Planning
Classifier: Topic :: Internet
Classifier: Typing :: Typed
Requires-Python: >=3.7
